tablaVerdad_I/tablaVerdad_I.v
// Code generated by Icestudio 0.2.2-dev
// Thu, 17 Nov 2016 19:40:00 GMT

`default_nettype none

module main (input vd9b5c7,
             input va55d5a,
             input v006143,
             output vfe8161);
 wire w0;
 wire w1;
 wire w2;
 wire w3;
 wire w4;
 wire w5;
 wire w6;
 wire w7;
 wire w8;
 wire w9;
 wire w10;
 wire w11;
 wire w12;
 wire w13;
 assign w0 = vd9b5c7;
 assign w2 = va55d5a;
 assign w4 = v006143;
 assign w9 = vd9b5c7;
 assign w10 = va55d5a;
 assign w11 = v006143;
 assign vfe8161 = w13;
 assign w9 = w0;
 assign w10 = w2;
 assign w11 = w4;
 main_logic_gate_and vbcc84a (
  .v0e28cb(w0),
  .v3ca442(w1),
  .vcbab45(w3)
 );
 main_logic_gate_and v3cc07d (
  .v0e28cb(w3),
  .v3ca442(w4),
  .vcbab45(w5)
 );
 main_logic_gate_or veb55c4 (
  .v0e28cb(w5),
  .v3ca442(w6),
  .vcbab45(w12)
 );
 main_logic_gate_or vaf19bb (
  .v3ca442(w10),
  .v0e28cb(w12),
  .vcbab45(w13)
 );
 main_logic_gate_and v8688cf (
  .vcbab45(w6),
  .v0e28cb(w7),
  .v3ca442(w8)
 );
 main_logic_gate_not v62acdc (
  .vcbab45(w1),
  .v0e28cb(w2)
 );
 main_logic_gate_not v9ecb77 (
  .vcbab45(w7),
  .v0e28cb(w9)
 );
 main_logic_gate_not vfd1241 (
  .vcbab45(w8),
  .v0e28cb(w11)
 );
endmodule

module main_logic_gate_and (input v0e28cb,
                            input v3ca442,
                            output vcbab45);
 wire w0;
 wire w1;
 wire w2;
 assign w0 = v0e28cb;
 assign w1 = v3ca442;
 assign vcbab45 = w2;
 main_logic_gate_and_basic_code_vf4938a vf4938a (
  .a(w0),
  .b(w1),
  .c(w2)
 );
endmodule

module main_logic_gate_and_basic_code_vf4938a (input a,
                                               input b,
                                               output c);
 // AND logic gate
 
 assign c = a & b;
endmodule

module main_logic_gate_or (input v0e28cb,
                           input v3ca442,
                           output vcbab45);
 wire w0;
 wire w1;
 wire w2;
 assign w0 = v0e28cb;
 assign w1 = v3ca442;
 assign vcbab45 = w2;
 main_logic_gate_or_basic_code_vf4938a vf4938a (
  .a(w0),
  .b(w1),
  .c(w2)
 );
endmodule

module main_logic_gate_or_basic_code_vf4938a (input a,
                                              input b,
                                              output c);
 // OR logic gate
 
 assign c = a | b;
endmodule

module main_logic_gate_not (input v0e28cb,
                            output vcbab45);
 wire w0;
 wire w1;
 assign w0 = v0e28cb;
 assign vcbab45 = w1;
 main_logic_gate_not_basic_code_vd54ca1 vd54ca1 (
  .a(w0),
  .c(w1)
 );
endmodule

module main_logic_gate_not_basic_code_vd54ca1 (input a,
                                               output c);
 // NOT logic gate
 
 assign c = ~ a;
endmodule

tablaVerdad_I/tablaVerdad_I_tb.v
// Code generated by Icestudio 0.2.2-dev
// Thu, 17 Nov 2016 19:40:09 GMT

// Testbench template

`default_nettype none
`define DUMPSTR(x) `"x.vcd`"
`timescale 10 ns / 1 ns

module main_tb ();
 
 // Simulation time: 100ns (10 * 10ns)
 parameter DURATION = 10;
 
 // Input/Output
 reg input_A;
 reg input_B;
 reg input_C;
 wire output_Out_1;
 
 // Module instance
 main MAIN (
  .vd9b5c7(input_A),
  .va55d5a(input_B),
  .v006143(input_C),
  .vfe8161(output_Out_1)
 );
 
 initial begin
  // File were to store the simulation results
  $dumpfile(`DUMPSTR(`VCD_OUTPUT));
  $dumpvars(0, main_tb);
 
  // TODO: initialize the registers here
  // e.g. input_value = 1;
  // e.g. #2 input_value = 0;
  input_A = 0;
  input_B = 0;
  input_C = 0;
  
  
  // JJVITON testing process
  
  //input_in_x =0;
  input_A = 1'b0;
  input_B = 1'b0;
  input_C = 1'b0;
  
  #50  // espero un poco para empezar.
  
  input_A = 1'b0;
  input_B = 1'b0;
  input_C = 1'b1;
  #20
  input_A = 1'b0;
  input_B = 1'b1;
  input_C = 1'b0;
  #20 
  input_A = 1'b0;
  input_B = 1'b1;
  input_C = 1'b1;
  #20  
  input_A = 1'b1;
  input_B = 1'b0;
  input_C = 1'b0;
  #20
  input_A = 1'b1;
  input_B = 1'b0;
  input_C = 1'b1;
  #20  
  input_A = 1'b1;
  input_B = 1'b1;
  input_C = 1'b0;
  #20 
  input_A = 1'b1;
  input_B = 1'b1;
  input_C = 1'b1;
  #20    
  
  
  
// JJVITON testing process  (fin) 
  
 
  #(DURATION) $display("End of simulation");
  $finish;
 end
 
endmodule

tablaVerdad_I/tablaVerdad_I_tb.vcd
$date
	Thu Nov 17 20:56:21 2016
$end
$version
	Icarus Verilog
$end
$timescale
	1ns
$end
$scope module main_tb $end
$var wire 1 ! output_Out_1 $end
$var reg 1 " input_A $end
$var reg 1 # input_B $end
$var reg 1 $ input_C $end
$scope module MAIN $end
$var wire 1 $ v006143 $end
$var wire 1 # va55d5a $end
$var wire 1 " vd9b5c7 $end
$var wire 1 ! vfe8161 $end
$var wire 1 % w0 $end
$var wire 1 & w10 $end
$var wire 1 ' w11 $end
$var wire 1 ( w2 $end
$var wire 1 ) w4 $end
$var wire 1 * w9 $end
$var wire 1 + w8 $end
$var wire 1 , w7 $end
$var wire 1 - w6 $end
$var wire 1 . w5 $end
$var wire 1 / w3 $end
$var wire 1 0 w13 $end
$var wire 1 1 w12 $end
$var wire 1 2 w1 $end
$scope module v3cc07d $end
$var wire 1 ) v3ca442 $end
$var wire 1 . vcbab45 $end
$var wire 1 3 w0 $end
$var wire 1 4 w1 $end
$var wire 1 5 w2 $end
$var wire 1 / v0e28cb $end
$scope module vf4938a $end
$var wire 1 3 a $end
$var wire 1 4 b $end
$var wire 1 5 c $end
$upscope $end
$upscope $end
$scope module v62acdc $end
$var wire 1 ( v0e28cb $end
$var wire 1 2 vcbab45 $end
$var wire 1 6 w0 $end
$var wire 1 7 w1 $end
$scope module vd54ca1 $end
$var wire 1 6 a $end
$var wire 1 7 c $end
$upscope $end
$upscope $end
$scope module v8688cf $end
$var wire 1 - vcbab45 $end
$var wire 1 8 w0 $end
$var wire 1 9 w1 $end
$var wire 1 : w2 $end
$var wire 1 + v3ca442 $end
$var wire 1 , v0e28cb $end
$scope module vf4938a $end
$var wire 1 8 a $end
$var wire 1 9 b $end
$var wire 1 : c $end
$upscope $end
$upscope $end
$scope module v9ecb77 $end
$var wire 1 * v0e28cb $end
$var wire 1 , vcbab45 $end
$var wire 1 ; w0 $end
$var wire 1 < w1 $end
$scope module vd54ca1 $end
$var wire 1 ; a $end
$var wire 1 < c $end
$upscope $end
$upscope $end
$scope module vaf19bb $end
$var wire 1 & v3ca442 $end
$var wire 1 0 vcbab45 $end
$var wire 1 = w0 $end
$var wire 1 > w1 $end
$var wire 1 ? w2 $end
$var wire 1 1 v0e28cb $end
$scope module vf4938a $end
$var wire 1 = a $end
$var wire 1 > b $end
$var wire 1 ? c $end
$upscope $end
$upscope $end
$scope module vbcc84a $end
$var wire 1 % v0e28cb $end
$var wire 1 2 v3ca442 $end
$var wire 1 / vcbab45 $end
$var wire 1 @ w0 $end
$var wire 1 A w1 $end
$var wire 1 B w2 $end
$scope module vf4938a $end
$var wire 1 @ a $end
$var wire 1 A b $end
$var wire 1 B c $end
$upscope $end
$upscope $end
$scope module veb55c4 $end
$var wire 1 . v0e28cb $end
$var wire 1 - v3ca442 $end
$var wire 1 1 vcbab45 $end
$var wire 1 C w0 $end
$var wire 1 D w1 $end
$var wire 1 E w2 $end
$scope module vf4938a $end
$var wire 1 C a $end
$var wire 1 D b $end
$var wire 1 E c $end
$upscope $end
$upscope $end
$scope module vfd1241 $end
$var wire 1 ' v0e28cb $end
$var wire 1 + vcbab45 $end
$var wire 1 F w0 $end
$var wire 1 G w1 $end
$scope module vd54ca1 $end
$var wire 1 F a $end
$var wire 1 G c $end
$upscope $end
$upscope $end
$upscope $end
$upscope $end
$enddefinitions $end
#0
$dumpvars
1G
0F
1E
1D
0C
0B
1A
0@
1?
0>
1=
1<
0;
1:
19
18
17
06
05
04
03
12
11
10
0/
0.
1-
1,
1+
0*
0)
0(
0'
0&
0%
0$
0#
0"
1!
$end
#500
0!
00
0?
0=
01
0E
0D
0-
0:
09
0+
0G
14
1)
1F
1'
1$
#700
1=
11
1E
1D
1-
1:
19
1+
1G
0A
02
07
1!
10
1?
04
0)
0F
0'
0$
16
1(
1>
1&
1#
#900
0=
01
0E
0D
0-
0:
09
0+
0G
14
1)
1F
1'
1$
#1100
13
1/
1B
19
1+
1G
1A
12
17
0!
00
0?
08
0,
0<
04
0)
0F
0'
0$
06
0(
0>
0&
0#
1@
1%
1;
1*
1"
#1300
1!
10
1?
1=
11
1E
1C
1.
15
09
0+
0G
14
1)
1F
1'
1$
#1500
0=
01
0E
03
0/
0B
0C
0.
05
19
1+
1G
0A
02
07
04
0)
0F
0'
0$
16
1(
1>
1&
1#
#1700
09
0+
0G
14
1)
1F
1'
1$
